polars_talib-0.1.5.dist-info/METADATA
polars_talib-0.1.5.dist-info/WHEEL
polars_talib-0.1.5.dist-info/licenses/LICENSE
polars_talib/__init__.py
polars_talib/utils.py
polars_talib/_polars_talib.abi3.so
polars_talib-0.1.5.dist-info/RECORD
