Metadata-Version: 2.4
Name: polars-talib
Version: 0.1.5
Classifier: Programming Language :: Rust
Classifier: Programming Language :: Python :: Implementation :: CPython
Classifier: Programming Language :: Python :: Implementation :: PyPy
Requires-Dist: polars >=0.18.0, <0.18.5 ; python_version < '3.8'
Requires-Dist: polars >=0.19 ; python_version >= '3.8'
License-File: LICENSE
Summary: Polars extension for Ta-Lib: Support Ta-Lib functions in Polars expressions
Keywords: polars-extension,talib,technical-analysis,TA-Lib,polars,rust,polars-expr
Author-email: yvictor <yvictor3141@gmail.com>
Requires-Python: >=3.7
